MANIFEST.in
README.md
setup.py
ekiNx/__init__.py
ekiNx/core.py
ekiNx/test1.py
ekiNx/test2.py
ekiNx/test3.py
ekiNx.egg-info/PKG-INFO
ekiNx.egg-info/SOURCES.txt
ekiNx.egg-info/dependency_links.txt
ekiNx.egg-info/entry_points.txt
ekiNx.egg-info/top_level.txt