Metadata-Version: 1.1
Name: ekiNx
Version: 0.0.3
Summary: This module provides complement functions for lib NetworkX
Home-page: https://github.com/charlesDADI/ekiNx
Author: Charles-Abner DADI @Ekimetrics
Author-email: charles-abner.dadi@ekimetrics.com
License: WTFPL
Platform: UNKNOWN
Classifier: Programming Language :: Python
Classifier: Development Status :: 1 - Planning
Classifier: License :: OSI Approved
Classifier: Natural Language :: French
Classifier: Operating System :: OS Independent
Classifier: Programming Language :: Python :: 2.7
Classifier: Topic :: Communications
